aiconn/__init__.py
aiconn/gemini.py
aiconn/utils.py
aiconn-0.0.3.dist-info/METADATA
aiconn-0.0.3.dist-info/WHEEL
aiconn-0.0.3.dist-info/top_level.txt
aiconn-0.0.3.dist-info/RECORD
